tableplus_macos_update_creds/__init__.py
tableplus_macos_update_creds/get_teamid.py
tableplus_macos_update_creds/update_creds.py
tableplus_macos_update_creds/update_password_in_keychain.py
tableplus_macos_update_creds-0.1.1.dist-info/LICENSE
tableplus_macos_update_creds-0.1.1.dist-info/METADATA
tableplus_macos_update_creds-0.1.1.dist-info/WHEEL
tableplus_macos_update_creds-0.1.1.dist-info/top_level.txt
tableplus_macos_update_creds-0.1.1.dist-info/RECORD
