Metadata-Version: 2.1
Name: tableplus-macos-update-creds
Version: 0.1.1
Summary: A python library to update credentials for a connection in TablePlus macOS client without using GUI
Author-email: Nikita Vaganov <nikita.e.vaganov@gmail.com>
Project-URL: Homepage, https://github.com/vaganov/tableplus-macos-update-creds
Project-URL: Bug Tracker, https://github.com/vaganov/tableplus-macos-update-creds/issues
Classifier: Programming Language :: Python :: 3
Classifier: License :: OSI Approved :: MIT License
Classifier: Operating System :: MacOS :: MacOS X
Requires-Python: >=3.7
License-File: LICENSE
